my_in_memory_db/__init__.py
my_in_memory_db/cli.py
my_in_memory_db/db.py
tests/__init__.py
tests/test_db.py
my_in_memory_db-0.0.1.dist-info/LICENSE
my_in_memory_db-0.0.1.dist-info/METADATA
my_in_memory_db-0.0.1.dist-info/WHEEL
my_in_memory_db-0.0.1.dist-info/entry_points.txt
my_in_memory_db-0.0.1.dist-info/top_level.txt
my_in_memory_db-0.0.1.dist-info/RECORD
